README.txt
setup.cfg
setup.py
Products/__init__.py
Products.FinisAfricae.egg-info/PKG-INFO
Products.FinisAfricae.egg-info/SOURCES.txt
Products.FinisAfricae.egg-info/dependency_links.txt
Products.FinisAfricae.egg-info/entry_points.txt
Products.FinisAfricae.egg-info/namespace_packages.txt
Products.FinisAfricae.egg-info/not-zip-safe
Products.FinisAfricae.egg-info/requires.txt
Products.FinisAfricae.egg-info/top_level.txt
Products/FinisAfricae/__init__.py
Products/FinisAfricae/content/Catalog.py
Products/FinisAfricae/content/CatalogObjectMods.py
Products/FinisAfricae/content/LendType.py
Products/FinisAfricae/content/LendableObject.py
Products/FinisAfricae/content/LibraryUser.py
Products/FinisAfricae/content/UserTypeContainer.py
Products/FinisAfricae/content/XMLArchetype.py
Products/FinisAfricae/content/__init__.py
Products/FinisAfricae/validators/XmlValidators.py
Products/FinisAfricae/validators/__init__.py
docs/HISTORY.txt