Metadata-Version: 1.0
Name: Products.FinisAfricae
Version: 0.5.1dev-r3
Summary: ILS (Integrated Library System) for Plone
Home-page: http://www.grigera.com.ar/software
Author: Juan Grigera
Author-email: juan@grigera.com.ar
License: GPL
Keywords: Archetypes Plone Zope
Platform: UNKNOWN
Classifier: Programming Language :: Python
Classifier: Topic :: Software Development :: Libraries :: Python Modules
Classifier: Framework :: Plone
Classifier: Framework :: Zope2
Classifier: Intended Audience :: Education
Classifier: License :: OSI Approved :: GNU General Public License (GPL)
Classifier: Operating System :: OS Independent
